a2a_reg_sdk/__init__.py
a2a_reg_sdk/client.py
a2a_reg_sdk/exceptions.py
a2a_reg_sdk/models.py
a2a_reg_sdk/publisher.py
a2a_reg_sdk-1.0.0.dist-info/METADATA
a2a_reg_sdk-1.0.0.dist-info/WHEEL
a2a_reg_sdk-1.0.0.dist-info/top_level.txt
a2a_reg_sdk-1.0.0.dist-info/RECORD
